zhiwowo/__init__.py
zhiwowo/zhiwowo.py
zhiwowo-1.0.0.dist-info/LICENSE
zhiwowo-1.0.0.dist-info/METADATA
zhiwowo-1.0.0.dist-info/WHEEL
zhiwowo-1.0.0.dist-info/top_level.txt
zhiwowo-1.0.0.dist-info/RECORD
